almaqso/__init__.py
almaqso/_analysis.py
almaqso/_casa_runner.py
almaqso/_download.py
almaqso/_logmgr.py
almaqso/_process.py
almaqso/_query.py
almaqso/_utils.py
almaqso/almaqso.py
almaqso/_templates/_export_fits.py
almaqso/_templates/_import_analysisUtils.py
almaqso/_templates/_importasdm_and_get_field_names.py
almaqso/_templates/_make_script.py
almaqso/_templates/_remove_target.py
almaqso/_templates/_selfcal_cube.py
almaqso/_templates/_selfcal_mfs.py
almaqso/_templates/_tclean_cube.py
almaqso/_templates/_tclean_mfs.py
almaqso/_templates/_tclean_mfs_spw.py
almaqso-1.6.0.dist-info/licenses/LICENSE
almaqso-1.6.0.dist-info/METADATA
almaqso-1.6.0.dist-info/WHEEL
almaqso-1.6.0.dist-info/top_level.txt
almaqso-1.6.0.dist-info/RECORD
