Metadata-Version: 2.4
Name: almaqso
Version: 1.6.0
Summary: Add your description here
Requires-Python: >=3.13
License-File: LICENSE
Requires-Dist: astroquery>=0.4.10
Requires-Dist: coloredlogs>=15.0.1
Requires-Dist: ipython>=9.0.2
Requires-Dist: matplotlib>=3.10.1
Requires-Dist: numpy>=2.2.4
Requires-Dist: pandas>=2.2.3
Requires-Dist: pyvo>=1.6.1
Requires-Dist: scipy>=1.15.2
Requires-Dist: setuptools>=78.0.2
Requires-Dist: spectral-cube>=0.6.6
Requires-Dist: tdqm>=0.0.1
Requires-Dist: tenacity>=9.1.2
Dynamic: license-file
